pdfapi_client/__init__.py
pdfapi_client/client.py
pdfapi_client/models.py
pdfapi_client-0.1.3.dist-info/METADATA
pdfapi_client-0.1.3.dist-info/WHEEL
pdfapi_client-0.1.3.dist-info/top_level.txt
pdfapi_client-0.1.3.dist-info/RECORD
