Metadata-Version: 2.2
Name: pdfapi-client
Version: 0.1.3
Summary: Python client for pdfapi.dev - HTML to PDF conversion service
Home-page: https://pdfapi.dev
Author: pdfapi.dev
Author-email: support@pdfapi.dev
Project-URL: Documentation, https://pdfapi.dev/
Project-URL: Source, https://github.com/pdfapi-dev-sdk/pdfapi-python-client
Keywords: pdf conversion html api client
Classifier: Development Status :: 5 - Production/Stable
Classifier: Intended Audience :: Developers
Classifier: Topic :: Software Development :: Libraries :: Python Modules
Classifier: Topic :: Printing
Classifier: License :: OSI Approved :: Apache Software License
Classifier: Programming Language :: Python :: 3
Classifier: Programming Language :: Python :: 3.7
Classifier: Programming Language :: Python :: 3.8
Classifier: Programming Language :: Python :: 3.9
Classifier: Programming Language :: Python :: 3.10
Classifier: Programming Language :: Python :: 3.11
Classifier: Operating System :: OS Independent
Requires-Python: >=3.7
Requires-Dist: requests>=2.25.0
Requires-Dist: urllib3>=1.26.0
Requires-Dist: typing-extensions>=4.0.0
Requires-Dist: certifi>=2021.10.8
Dynamic: author
Dynamic: author-email
Dynamic: classifier
Dynamic: description
Dynamic: description-content-type
Dynamic: home-page
Dynamic: keywords
Dynamic: project-url
Dynamic: requires-dist
Dynamic: requires-python
Dynamic: summary
